dftools/database/snowflake/__init__.py
dftools/database/snowflake/connection.py
dftools/database/snowflake/connection_adapter.py
dftools/database/snowflake/connection_metadata.py
dftools/database/snowflake/connection_util.py
dftools/database/snowflake/structure_decoder.py
dftools/database/snowflake/system_queries.py
dftools_snowflake-0.1.1.dist-info/LICENSE.md
dftools_snowflake-0.1.1.dist-info/METADATA
dftools_snowflake-0.1.1.dist-info/WHEEL
dftools_snowflake-0.1.1.dist-info/top_level.txt
dftools_snowflake-0.1.1.dist-info/RECORD
