Metadata-Version: 2.1
Name: dftools-snowflake
Version: 0.1.1
Summary: Data Flooder Tools - Snowflake Package
Author: Data Flooder
Author-email: Lirav DUVSHANI <lirav.duvshani@dataflooder.com>
License: Apache License
Project-URL: Homepage, https://github.com/dataflooder/dftools-core
Keywords: df,dataflooder,dftools,data,dataengineering,snowflake
Classifier: License :: OSI Approved :: Apache Software License
Classifier: Programming Language :: Python :: 3
Classifier: Development Status :: 3 - Alpha
Requires-Python: >=3.7.9
License-File: LICENSE.md
Requires-Dist: snowflake-connector-python
Requires-Dist: dftools-core
Provides-Extra: dev
